rungs/InlineMenu.py
rungs/__init__.py
rungs/main.py
rungs-1.0.12.dist-info/entry_points.txt
rungs-1.0.12.dist-info/licenses/LICENSE
rungs-1.0.12.dist-info/WHEEL
rungs-1.0.12.dist-info/METADATA
rungs-1.0.12.dist-info/RECORD
