Metadata-Version: 2.4
Name: rungs
Version: 1.0.12
Summary: Menu for Fuzzy Linux Procedures
Keywords: menu,maintenance,procedure,fuzzy
Author-email: Joe Defen <joedef@gmail.com>
Requires-Python: >=3.8
Classifier: Programming Language :: Python :: 3
Classifier: License :: OSI Approved :: MIT License
Classifier: Operating System :: POSIX :: Linux
License-File: LICENSE
Project-URL: Bug Tracker, https://github.com/joedefen/rungs/issues
Project-URL: Homepage, https://github.com/joedefen/rungs
